<annotation>
  <folder>/home/raahish/Documents/Codes/darkflow-master/Dataset/olx_images_jpg/Batch</folder>
  <filename>4223.jpg</filename>
  <segmented>0</segmented>
  <size>
    <width>259</width>
    <height>461</height>
    <depth>3</depth>
  </size>
  <object>
    <name>split_AC</name>
    <pose>Unspecified</pose>
    <truncated>0</truncated>
    <difficult>0</difficult>
    <bndbox>
      <xmin>1</xmin>
      <ymin>108</ymin>
      <xmax>252</xmax>
      <ymax>163</ymax>
    </bndbox>
  </object>
  <object>
    <name>split_AC</name>
    <pose>Unspecified</pose>
    <truncated>0</truncated>
    <difficult>0</difficult>
    <bndbox>
      <xmin>1</xmin>
      <ymin>149</ymin>
      <xmax>257</xmax>
      <ymax>253</ymax>
    </bndbox>
  </object>
</annotation>
